nlpswift/__init__.py
nlpswift/logger.py
nlpswift/search.py
nlpswift/timer.py
nlpswift/db/__init__.py
nlpswift/db/es_helper.py
nlpswift/db/minio_helper.py
nlpswift/db/mysql_helper.py
nlpswift/db/neo4j_helper.py
nlpswift/db/redis_helper.py
nlpswift/evaluation/__init__.py
nlpswift/evaluation/ner_evaluation.py
nlpswift/evaluation/rag_evaluation.py
nlpswift/evaluation/ner_eval_core/__init__.py
nlpswift/evaluation/ner_eval_core/ner_eval.py
nlpswift/extractor/__init__.py
nlpswift/extractor/json_helper.py
nlpswift/message/__init__.py
nlpswift-0.0.7.dist-info/LICENSE
nlpswift-0.0.7.dist-info/METADATA
nlpswift-0.0.7.dist-info/WHEEL
nlpswift-0.0.7.dist-info/top_level.txt
nlpswift-0.0.7.dist-info/RECORD
