Metadata-Version: 2.1
Name: nlpswift
Version: 0.0.7
Summary: my nlpswift
Home-page: https://github.com/zhpmatrix/nlpswift
Download-URL: https://pypi.tuna.tsinghua.edu.cn/simple
Author: zhp.matrix
Requires-Python: >=3.7
License-File: LICENSE
Requires-Dist: setuptools ==58.2.0
Requires-Dist: wheel ==0.43.0
Requires-Dist: pymysql
Requires-Dist: py2neo
Requires-Dist: redis
Requires-Dist: baidusearch
Requires-Dist: gunicorn
Requires-Dist: gevent
Requires-Dist: flask
Requires-Dist: ragas
Requires-Dist: langchain
